apiruns/__init__.py
apiruns/clients.py
apiruns/exceptions.py
apiruns/main.py
apiruns/serializers.py
apiruns/services.py
apiruns/utils.py
apiruns-0.0.5.dist-info/entry_points.txt
apiruns-0.0.5.dist-info/LICENSE
apiruns-0.0.5.dist-info/WHEEL
apiruns-0.0.5.dist-info/METADATA
apiruns-0.0.5.dist-info/RECORD
