Metadata-Version: 2.1
Name: apiruns
Version: 0.0.5
Summary: Apiruns CLI is a tool to make self-configurable rest API.
Home-page: https://github.com/apiruns/apiruns-cli
License: MIT
Keywords: Poetry,CLI,Apiruns,Packages,Packaging,Docker,No-code,Low-code
Author: Jose Salas
Author-email: jose.salas@apiruns.com
Requires-Python: >=3.7,<4.0
Classifier: License :: OSI Approved :: MIT License
Classifier: Programming Language :: Python :: 3
Classifier: Programming Language :: Python :: 3.10
Classifier: Programming Language :: Python :: 3.7
Classifier: Programming Language :: Python :: 3.8
Classifier: Programming Language :: Python :: 3.9
Requires-Dist: Cerberus (>=1.3.4,<2.0.0)
Requires-Dist: PyYAML (>=6.0,<7.0)
Requires-Dist: httpx (>=0.23.0,<0.24.0)
Requires-Dist: requests (>=2.28.1,<3.0.0)
Requires-Dist: typer[all] (>=0.6.1,<0.7.0)
Project-URL: Documentation, https://github.com/apiruns/apiruns-cli
Project-URL: Repository, https://github.com/apiruns/apiruns-cli
